safeds/__init__.py
safeds/_config/__init__.py
safeds/_config/_polars.py
safeds/_config/_torch.py
safeds/_typing/__init__.py
safeds/_utils/__init__.py
safeds/_utils/_collections.py
safeds/_utils/_hashing.py
safeds/_utils/_lazy.py
safeds/_utils/_plotting.py
safeds/_utils/_random.py
safeds/_utils/_string.py
safeds/_validation/__init__.py
safeds/_validation/_check_bounds_module.py
safeds/_validation/_check_column_has_no_missing_values.py
safeds/_validation/_check_column_is_numeric_module.py
safeds/_validation/_check_columns_dont_exist_module.py
safeds/_validation/_check_columns_exist_module.py
safeds/_validation/_check_indices_module.py
safeds/_validation/_check_row_counts_are_equal_module.py
safeds/_validation/_check_schema_module.py
safeds/_validation/_check_time_zone_module.py
safeds/_validation/_convert_and_check_datetime_format_module.py
safeds/_validation/_normalize_and_check_file_path_module.py
safeds/data/__init__.py
safeds/data/image/__init__.py
safeds/data/image/_utils/__init__.py
safeds/data/image/_utils/_image_transformation_error_and_warning_checks.py
safeds/data/image/containers/__init__.py
safeds/data/image/containers/_empty_image_list.py
safeds/data/image/containers/_image.py
safeds/data/image/containers/_image_list.py
safeds/data/image/containers/_multi_size_image_list.py
safeds/data/image/containers/_single_size_image_list.py
safeds/data/image/typing/__init__.py
safeds/data/image/typing/_image_size.py
safeds/data/labeled/__init__.py
safeds/data/labeled/containers/__init__.py
safeds/data/labeled/containers/_dataset.py
safeds/data/labeled/containers/_image_dataset.py
safeds/data/labeled/containers/_tabular_dataset.py
safeds/data/labeled/containers/_time_series_dataset.py
safeds/data/tabular/__init__.py
safeds/data/tabular/containers/__init__.py
safeds/data/tabular/containers/_cell.py
safeds/data/tabular/containers/_column.py
safeds/data/tabular/containers/_lazy_cell.py
safeds/data/tabular/containers/_lazy_vectorized_row.py
safe_ds-0.31.0.dist-info/LICENSE
safe_ds-0.31.0.dist-info/METADATA
safe_ds-0.31.0.dist-info/WHEEL
safe_ds-0.31.0.dist-info/RECORD
