Metadata-Version: 2.3
Name: safe-ds
Version: 0.31.0
Summary: A user-friendly library for Data Science in Python.
License: MIT
Keywords: data-science,machine-learning,usability,learnability
Author: Lars Reimann
Author-email: mail@larsreimann.com
Requires-Python: >=3.12,<3.14
Classifier: License :: OSI Approved :: MIT License
Classifier: Programming Language :: Python :: 3
Classifier: Programming Language :: Python :: 3.12
Classifier: Programming Language :: Python :: 3.13
Requires-Dist: apipkg (>=3.0.2,<4.0.0)
Requires-Dist: matplotlib (>=3.6.3,<4.0.0)
Requires-Dist: numpy (<3.0.0)
Requires-Dist: pillow (>=9.5,<12.0)
Requires-Dist: polars[numpy,pyarrow] (>=1.7.1,<2.0.0)
Requires-Dist: scikit-learn (>=1.2.0,<2.0.0)
Requires-Dist: statsmodels (>=0.14.1,<0.15.0)
Requires-Dist: torch (>=2.7.0,<3.0.0)
Requires-Dist: torchvision (>=0.22.0,<0.23.0)
Requires-Dist: transformers (>=4.40.2,<5.0.0)
Requires-Dist: xxhash (>=3.4.1,<4.0.0)
Project-URL: Documentation, https://library.safeds.com
Project-URL: Repository, https://github.com/Safe-DS/Library
